abode/__init__.py
abode/activate.py
abode/create.py
abode/deploy.py
abode/env.py
abode/file_io.py
abode/install.py
abode/list.py
abode/update.py
abode-0.1.4.data/scripts/abode
abode-0.1.4.dist-info/LICENSE
abode-0.1.4.dist-info/METADATA
abode-0.1.4.dist-info/WHEEL
abode-0.1.4.dist-info/top_level.txt
abode-0.1.4.dist-info/RECORD
